blue_shell_client/__init__.py
blue_shell_client/client.py
blue_shell_client/test_client.py
blue_shell_client-0.2.0.dist-info/METADATA
blue_shell_client-0.2.0.dist-info/WHEEL
blue_shell_client-0.2.0.dist-info/RECORD
