Metadata-Version: 2.1
Name: blue_shell_client
Version: 0.2.0
Summary: A python client for tracking tests
Author: Shayan Sadeghieh
Author-email: shayan.sadeghieh@gmail.com
Requires-Python: >=3.12,<4.0
Classifier: Programming Language :: Python :: 3
Classifier: Programming Language :: Python :: 3.12
Requires-Dist: requests (>=2.32.3,<3.0.0)
